etubeapi/__init__.py
etubeapi/lib.py
etubeapi/main.py
etubeapi-0.1.2.dist-info/licenses/LICENSE
etubeapi-0.1.2.dist-info/METADATA
etubeapi-0.1.2.dist-info/WHEEL
etubeapi-0.1.2.dist-info/entry_points.txt
etubeapi-0.1.2.dist-info/top_level.txt
etubeapi-0.1.2.dist-info/RECORD
