Metadata-Version: 2.4
Name: etubeapi
Version: 0.1.2
Summary: CLI tool that allows for interacting with Shimano's E-Tube API
Author-email: Norbert Arkadiusz Görke <me@ngorke.dev>, Magnust Hektoen Steensland <mag.steensland@gmail.com>
License-Expression: Apache-2.0
Project-URL: Repository, https://github.com/reven-project/etubeapi.git
License-File: LICENSE
Requires-Dist: httpx~=0.28.1
Requires-Dist: beautifulsoup4~=4.13
Requires-Dist: typer~=0.16.0
Requires-Dist: rich~=13.9
Requires-Dist: cattrs~=25.1
Requires-Dist: PyYAML~=6.0
Dynamic: license-file
